echo_mcp_server_for_testing/__init__.py
echo_mcp_server_for_testing/_version.py
echo_mcp_server_for_testing/main.py
echo_mcp_server_for_testing-0.1.5.dist-info/licenses/LICENSE
echo_mcp_server_for_testing-0.1.5.dist-info/METADATA
echo_mcp_server_for_testing-0.1.5.dist-info/WHEEL
echo_mcp_server_for_testing-0.1.5.dist-info/entry_points.txt
echo_mcp_server_for_testing-0.1.5.dist-info/top_level.txt
echo_mcp_server_for_testing-0.1.5.dist-info/RECORD
