Metadata-Version: 2.4
Name: echo-mcp-server-for-testing
Version: 0.1.5
Summary: A simple echo MCP (Model Context Protocol) Server for testing MCP Clients
Author-email: Piet Brömmel <piet.broemmel@gmail.com>
License-Expression: MIT
Project-URL: Homepage, https://github.com/piebro/mcp-server-for-testing
Project-URL: Bug Tracker, https://github.com/piebro/mcp-server-for-testing/issues
Keywords: mcp,server,testing
Classifier: Development Status :: 4 - Beta
Classifier: Intended Audience :: Developers
Classifier: Programming Language :: Python :: 3
Classifier: Programming Language :: Python :: 3.10
Requires-Python: >=3.10
License-File: LICENSE
Requires-Dist: ruff
Requires-Dist: mcp
Dynamic: license-file
